nice_auth/__init__.py
nice_auth/exceptions.py
nice_auth/services.py
nice_auth/utils.py
nice_auth-0.1.5.dist-info/LICENSE
nice_auth-0.1.5.dist-info/METADATA
nice_auth-0.1.5.dist-info/WHEEL
nice_auth-0.1.5.dist-info/top_level.txt
nice_auth-0.1.5.dist-info/RECORD
