Metadata-Version: 2.1
Name: nice-auth
Version: 0.1.5
Summary: A Python library for NICE authentication
Home-page: https://github.com/RUNNERS-IM/python-nice-auth
Author: RUNNERS
Author-email: dev@runners.im
License: UNKNOWN
Platform: UNKNOWN
Classifier: Programming Language :: Python :: 3
Classifier: License :: OSI Approved :: MIT License
Classifier: Operating System :: OS Independent
Requires-Python: >=3.6
Requires-Dist: requests
Requires-Dist: pycryptodome
